aropha/__init__.py
aropha/arduino.py
aropha/util.py
aropha-0.0.1.dist-info/LICENSE
aropha-0.0.1.dist-info/METADATA
aropha-0.0.1.dist-info/WHEEL
aropha-0.0.1.dist-info/top_level.txt
aropha-0.0.1.dist-info/RECORD
