Metadata-Version: 2.1
Name: aropha
Version: 0.0.1
Summary: For machine learning
Home-page: https://github.com/aropha/aropha
Author: Aropha Inc.
Author-email: sales@aropha.com
License: UNKNOWN
Platform: UNKNOWN
Classifier: Programming Language :: Python :: 3
Classifier: License :: OSI Approved :: MIT License
Classifier: Operating System :: OS Independent
Requires-Python: >=3.7
License-File: LICENSE
